protein_folding_environment/__init__.py
protein_folding_environment/base_environment.py
protein_folding_environment/base_environment_2d.py
protein_folding_environment/environement_triunghiular.py
protein_folding_environment/environment_2d.py
protein_folding_environment/environment_3d.py
protein_folding_environment/environment_LRF.py
utils/__init__.py
utils/input_handler.py
utils/movement_utils.py
utils/plotting_utils.py
protein_folding_gym_utils-0.0.1.dist-info/METADATA
protein_folding_gym_utils-0.0.1.dist-info/WHEEL
protein_folding_gym_utils-0.0.1.dist-info/top_level.txt
protein_folding_gym_utils-0.0.1.dist-info/RECORD
