Metadata-Version: 2.1
Name: protein-folding-gym-utils
Version: 0.0.1
Summary: Package with Reinforcement Learning Environments for Protein Folding
Author: Muscalagiu Anca Ioana
Author-email: ancamuscalagiu1@gmail.com
License: MIT
Keywords: protein,folding,reinforcement
Classifier: Development Status :: 4 - Beta
Classifier: Intended Audience :: Developers
Classifier: License :: OSI Approved :: MIT License
Classifier: Programming Language :: Python :: 3
Classifier: Operating System :: OS Independent
Requires-Dist: bio (==1.5.9)
Requires-Dist: biopython (==1.81)
Requires-Dist: biothings-client (==0.3.0)
Requires-Dist: certifi (==2022.12.7)
Requires-Dist: charset-normalizer (==3.1.0)
Requires-Dist: cloudpickle (==2.2.1)
Requires-Dist: contourpy (==1.0.7)
Requires-Dist: cycler (==0.11.0)
Requires-Dist: fonttools (==4.39.3)
Requires-Dist: gprofiler-official (==1.0.0)
Requires-Dist: gym (==0.26.2)
Requires-Dist: gym-notices (==0.0.8)
Requires-Dist: importlib-metadata (==6.6.0)
Requires-Dist: importlib-resources (==5.12.0)
Requires-Dist: joblib (==1.2.0)
Requires-Dist: kiwisolver (==1.4.4)
Requires-Dist: matplotlib (==3.7.1)
Requires-Dist: mygene (==3.2.2)
Requires-Dist: numpy (==1.23.5)
Requires-Dist: packaging (==23.1)
Requires-Dist: pandas (==2.0.1)
Requires-Dist: Pillow (==9.5.0)
Requires-Dist: platformdirs (==3.3.0)
Requires-Dist: pooch (==1.7.0)
Requires-Dist: pyparsing (==3.0.9)
Requires-Dist: python-dateutil (==2.8.2)
Requires-Dist: pytz (==2023.3)
Requires-Dist: requests (==2.28.2)
Requires-Dist: scikit-learn (==1.2.2)
Requires-Dist: scipy (==1.10.1)
Requires-Dist: six (==1.16.0)
Requires-Dist: threadpoolctl (==3.1.0)
Requires-Dist: tqdm (==4.65.0)
Requires-Dist: tzdata (==2023.3)
Requires-Dist: urllib3 (==1.26.15)
Requires-Dist: zipp (==3.15.0)
